README.md
setup.py
logging_reset.egg-info/PKG-INFO
logging_reset.egg-info/SOURCES.txt
logging_reset.egg-info/dependency_links.txt
logging_reset.egg-info/top_level.txt
logreset/__init__.py
logreset/logreset.py